python_random_strings/__init__.py
python_random_strings/python_random_strings.py
python_random_strings-0.3.dist-info/LICENSE
python_random_strings-0.3.dist-info/METADATA
python_random_strings-0.3.dist-info/WHEEL
python_random_strings-0.3.dist-info/top_level.txt
python_random_strings-0.3.dist-info/RECORD
