Metadata-Version: 2.1
Name: python-random-strings
Version: 0.3
Summary: a python lib for generate random string and digits and special characters or A combination of them
Home-page: https://github.com/TorhamDev/python-random-strings
Author: Torham
Author-email: torhamdev@gmail.com
License: gpl-3.0
Keywords: python random strings,generate random string,generate random digits,generate random hex digits,generate random oct digits,generate random punctuation,generate random printable,generate random lower case,generate random upper case,generate random letters
Classifier: License :: OSI Approved :: GNU Lesser General Public License v3 or later (LGPLv3+)
Classifier: Programming Language :: Python :: 3.6
Classifier: Programming Language :: Python :: 3.7
Classifier: Programming Language :: Python :: 3.8
Classifier: Programming Language :: Python :: 3.9
Requires-Python: >=3.6.0
License-File: LICENSE
